narrator/__init__.py
narrator/narrator.py
narrator-0.0.0.4.dist-info/LICENSE
narrator-0.0.0.4.dist-info/METADATA
narrator-0.0.0.4.dist-info/WHEEL
narrator-0.0.0.4.dist-info/top_level.txt
narrator-0.0.0.4.dist-info/RECORD
