Metadata-Version: 2.1
Name: narrator
Version: 0.0.0.4
Summary: A set of functions that process and create descriptive summary visualizations to help develop a broader narrative through-line of tweet data.
Home-page: https://github.com/lingeringcode/narrator/
Author: Chris A. Lindgren
Author-email: chris.a.lindgren@gmail.com
License: UNKNOWN
Download-URL: https://github.com/lingeringcode/narrator/
Keywords: data processing,descriptive statistics,data narratives,temporal charts
Platform: UNKNOWN
Requires-Dist: pandas
Requires-Dist: numpy
Requires-Dist: emoji
Requires-Dist: nltk
Requires-Dist: matplot
